ordo/__init__.py
ordo/ordo.js
ordo-0.3.3.dist-info/METADATA
ordo-0.3.3.dist-info/WHEEL
ordo-0.3.3.dist-info/top_level.txt
ordo-0.3.3.dist-info/RECORD
