Metadata-Version: 2.1
Name: ordo
Version: 0.3.3
Summary: A lightweight feedback tool for Jupyter
Home-page: https://github.com/nbgallery/ordo
Author: Andre J. Michell
Author-email: andre.j.michell2@gmail.com
License: UNKNOWN
Keywords: nbgallery,Jupyter,grading
Platform: UNKNOWN
